Metadata-Version: 1.1
Name: dataexplore-plot
Version: 0.0.1
Summary: Plotting module for use in data exploration for ML and Kaggle
Home-page: https://github.com/spidezad/dataexplore_plot
Author: Tan Kok Hua
Author-email: kokhuatan.fl@gmail.com
License: BSD
Download-URL: https://github.com/spidezad/dataexplore_plot/tarball/0.0.1
Platform: UNKNOWN
Classifier: Development Status :: 3 - Alpha
Classifier: Intended Audience :: Developers
Classifier: Programming Language :: Python :: 3
